github_oidc/client.py
github_oidc/debug.py
github_oidc/server.py
fastapi_github_oidc-0.3.0.dist-info/METADATA
fastapi_github_oidc-0.3.0.dist-info/WHEEL
fastapi_github_oidc-0.3.0.dist-info/licenses/LICENSE
fastapi_github_oidc-0.3.0.dist-info/RECORD
