Metadata-Version: 2.4
Name: fastapi-github-oidc
Version: 0.3.0
Summary: FastAPI middleware to authenticate Github OIDC Tokens
License-File: LICENSE
Requires-Python: >=3.13
